MANIFEST.in
README.rst
requirements.txt
setup.py
thoth/worker/__init__.py
thoth/worker/exceptions.py
thoth/worker/foreach.py
thoth/worker/selective.py
thoth/worker/storages.py
thoth/worker/utils.py
thoth/worker/tasks/__init__.py
thoth/worker/tasks/keywords.py
thoth/worker/tasks/project2vec.py
thoth/worker/tasks/pypi.py
thoth/worker/tasks/sync.py
thoth_worker.egg-info/PKG-INFO
thoth_worker.egg-info/SOURCES.txt
thoth_worker.egg-info/dependency_links.txt
thoth_worker.egg-info/not-zip-safe
thoth_worker.egg-info/requires.txt
thoth_worker.egg-info/top_level.txt